horilla_crm/__init__.py
horilla_crm/accounts/__init__.py
horilla_crm/accounts/admin.py
horilla_crm/accounts/apps.py
horilla_crm/accounts/filters.py
horilla_crm/accounts/floating_menu.py
horilla_crm/accounts/forms.py
horilla_crm/accounts/methods.py
horilla_crm/accounts/models.py
horilla_crm/accounts/scheduler.py
horilla_crm/accounts/signals.py
horilla_crm/accounts/tests.py
horilla_crm/accounts/urls.py
horilla_crm/accounts/views.py
horilla_crm/accounts/migrations/0001_initial.py
horilla_crm/accounts/migrations/__init__.py
horilla_crm/accounts/templatetags/__init__.py
horilla_crm/activity/__init__.py
horilla_crm/activity/admin.py
horilla_crm/activity/apps.py
horilla_crm/activity/filters.py
horilla_crm/activity/forms.py
horilla_crm/activity/methods.py
horilla_crm/activity/models.py
horilla_crm/activity/scheduler.py
horilla_crm/activity/signals.py
horilla_crm/activity/tests.py
horilla_crm/activity/urls.py
horilla_crm/activity/views.py
horilla_crm/activity/migrations/0001_initial.py
horilla_crm/activity/migrations/__init__.py
horilla_crm/activity/templatetags/__init__.py
horilla_crm/campaigns/__init__.py
horilla_crm/campaigns/admin.py
horilla_crm/campaigns/apps.py
horilla_crm/campaigns/filters.py
horilla_crm/campaigns/floating_menu.py
horilla_crm/campaigns/forms.py
horilla_crm/campaigns/methods.py
horilla_crm/campaigns/models.py
horilla_crm/campaigns/scheduler.py
horilla_crm/campaigns/signals.py
horilla_crm/campaigns/tests.py
horilla_crm/campaigns/urls.py
horilla_crm/campaigns/views.py
horilla_crm/campaigns/migrations/0001_initial.py
horilla_crm/campaigns/migrations/0002_initial.py
horilla_crm/campaigns/migrations/0003_initial.py
horilla_crm/campaigns/migrations/__init__.py
horilla_crm/campaigns/templatetags/__init__.py
horilla_crm/contacts/__init__.py
horilla_crm/contacts/admin.py
horilla_crm/contacts/apps.py
horilla_crm/contacts/filters.py
horilla_crm/contacts/floating_menu.py
horilla_crm/contacts/forms.py
horilla_crm/contacts/methods.py
horilla_crm/contacts/models.py
horilla_crm-1.0.0.dist-info/METADATA
horilla_crm-1.0.0.dist-info/WHEEL
horilla_crm-1.0.0.dist-info/top_level.txt
horilla_crm-1.0.0.dist-info/RECORD
