Metadata-Version: 2.4
Name: horilla-crm
Version: 1.0.0
Summary: Horilla CRM Django apps package
Home-page: https://github.com/horilla-opensource/horilla
Author: Your Name
Author-email: your_email@example.com
Classifier: Programming Language :: Python :: 3
Classifier: Framework :: Django
Classifier: License :: OSI Approved :: MIT License
Classifier: Operating System :: OS Independent
Dynamic: author
Dynamic: author-email
Dynamic: classifier
Dynamic: home-page
Dynamic: summary
